revisor_codigo/cli.py
revisor_codigo-0.1.4.dist-info/METADATA
revisor_codigo-0.1.4.dist-info/WHEEL
revisor_codigo-0.1.4.dist-info/entry_points.txt
revisor_codigo-0.1.4.dist-info/RECORD
