Metadata-Version: 2.1
Name: revisor-codigo
Version: 0.1.4
Summary: Revisor de código que usa LLMs
Home-page: https://github.com/SEU_USUARIO/SEU_REPO
License: MIT
Author: Jorge Luiz Facina
Requires-Python: >=3.9,<4.0
Classifier: License :: OSI Approved :: MIT License
Classifier: Programming Language :: Python :: 3
Classifier: Programming Language :: Python :: 3.9
Classifier: Programming Language :: Python :: 3.10
Classifier: Programming Language :: Python :: 3.11
Classifier: Programming Language :: Python :: 3.12
Requires-Dist: anthropic (==0.57.1)
Requires-Dist: gitpython (==3.1.44)
Requires-Dist: google-genai (>=1.25.0,<2.0.0)
Requires-Dist: openai (>=1.95.1,<2.0.0)
Requires-Dist: python-dotenv (>=1.1.1,<2.0.0)
